physics/__init__.py
physics/charge_network.py
physics/charges.py
physics/constants.py
visualization/__init__.py
visualization/colors.py
visualization/numbers.py
visualization/screen.py
visualization/settings.py
visualization/simulation.py
electripy-0.0.2.dist-info/LICENSE
electripy-0.0.2.dist-info/METADATA
electripy-0.0.2.dist-info/WHEEL
electripy-0.0.2.dist-info/top_level.txt
electripy-0.0.2.dist-info/RECORD
