Metadata-Version: 2.1
Name: electripy
Version: 0.0.2
Summary: Visualize the electric field of a point charge network
Home-page: https://github.com/pypa/sampleproject
Author: Dylan Tintenfich
Author-email: tintenfichdylan05@gmail.com
License: UNKNOWN
Project-URL: Bug Tracker, https://github.com/dylannalex/electripy
Platform: UNKNOWN
Classifier: Programming Language :: Python :: 3
Classifier: License :: OSI Approved :: MIT License
Requires-Python: >=3.6
License-File: LICENSE
